oebl_irs_workflow/.gitignore
oebl_irs_workflow/__init__.py
oebl_irs_workflow/admin.py
oebl_irs_workflow/api_urls_v1.py
oebl_irs_workflow/api_views.py
oebl_irs_workflow/apps.py
oebl_irs_workflow/json_schema_oebl_workflow_2.json
oebl_irs_workflow/migrations/0001_initial.py
oebl_irs_workflow/migrations/__init__.py
oebl_irs_workflow/models.py
oebl_irs_workflow/parse_jsonschema.py
oebl_irs_workflow/serializers.py
oebl_irs_workflow/urls.py
oebl_irs_workflow-0.1.9.dist-info/WHEEL
oebl_irs_workflow-0.1.9.dist-info/METADATA
oebl_irs_workflow-0.1.9.dist-info/RECORD
